{
  "annotations": {
    "list": [
      {
        "builtIn": 1,
        "datasource": {
          "type": "datasource",
          "uid": "metric_data_source"
        },
        "enable": true,
        "hide": true,
        "iconColor": "rgba(0, 211, 255, 1)",
        "name": "Annotations & Alerts",
        "type": "dashboard"
      }
    ]
  },
  "editable": true,
  "gnetId": null,
  "graphTooltip": 0,
  "id": 1,
  "links": [],
  "panels": [
    {
      "datasource": {
        "type": "prometheus",
        "uid": "metric_data_source"
      },
      "gridPos": {
        "h": 9,
        "w": 12,
        "x": 0,
        "y": 0
      },
      "id": 1,
      "options": {
        "colorMode": "value",
        "graphMode": "area",
        "justifyMode": "auto",
        "orientation": "auto",
        "reduceOptions": {
          "calcs": [
            "lastNotNull"
          ],
          "fields": "",
          "values": false
        },
        "showThresholdLabels": false,
        "showThresholdMarkers": true
      },
      "pluginVersion": "10.0.3",
      "targets": [
        {
          "datasource": {
            "type": "prometheus",
            "uid": "metric_data_source"
          },
          "editorMode": "code",
          "expr": "sum(http_requests_total) by (instance)",
          "legendFormat": "Active Sessions",
          "range": true,
          "refId": "A"
        }
      ],
      "title": "API Active Sessions",
      "type": "timeseries"
    },
    {
      "datasource": {
        "type": "prometheus",
        "uid": "metric_data_source"
      },
      "gridPos": {
        "h": 9,
        "w": 12,
        "x": 12,
        "y": 0
      },
      "id": 2,
      "options": {
        "colorMode": "value",
        "graphMode": "area",
        "justifyMode": "auto",
        "orientation": "auto",
        "reduceOptions": {
          "calcs": [
            "lastNotNull"
          ],
          "fields": "",
          "values": false
        },
        "showThresholdLabels": false,
        "showThresholdMarkers": true
      },
      "pluginVersion": "10.0.3",
      "targets": [
        {
          "datasource": {
            "type": "prometheus",
            "uid": "metric_data_source"
          },
          "editorMode": "code",
          "expr": "rate(http_request_duration_seconds_sum[1m]) / rate(http_request_duration_seconds_count[1m])",
          "legendFormat": "Average Latency (ms)",
          "range": true,
          "refId": "A"
        }
      ],
      "title": "API Average Latency (Last 1 Minute)",
      "type": "timeseries"
    }
  ],
  "refresh": "30s",
  "schemaVersion": 38,
  "style": "dark",
  "tags": [
    "system",
    "monitor"
  ],
  "templating": {
    "list": []
  },
  "time": {
    "from": "now-2h",
    "to": "now"
  },
  "timepicker": {},
  "timezone": "",
  "title": "API Health Check Dashboard",
  "uid": "api-health-check-dashboard-v2",
  "version": 1
}